hsms/__init__.py
hsms/clvm/__init__.py
hsms/clvm/disasm.py
hsms/clvm_serde/__init__.py
hsms/cmds/__init__.py
hsms/cmds/hsm_dump_sb.py
hsms/cmds/hsm_dump_us.py
hsms/cmds/hsm_test_spend.py
hsms/cmds/hsmgen.py
hsms/cmds/hsmmerge.py
hsms/cmds/hsmpk.py
hsms/cmds/hsms.py
hsms/cmds/hsmwizard.py
hsms/cmds/poser_gen.py
hsms/cmds/poser_verify.py
hsms/cmds/qrint.py
hsms/consensus/__init__.py
hsms/consensus/conditions.py
hsms/core/__init__.py
hsms/core/signing_hints.py
hsms/core/unsigned_spend.py
hsms/debug/__init__.py
hsms/debug/debug_spend_bundle.py
hsms/process/__init__.py
hsms/process/sign.py
hsms/puzzles/conlang.py
hsms/puzzles/p2_conditions.py
hsms/puzzles/p2_delegated_puzzle_or_hidden_puzzle.py
hsms/util/__init__.py
hsms/util/byte_chunks.py
hsms/util/qrint_encoding.py
hsms/util/type_tree.py
quex_hsms-0.1.dev157.dist-info/LICENSE
quex_hsms-0.1.dev157.dist-info/METADATA
quex_hsms-0.1.dev157.dist-info/WHEEL
quex_hsms-0.1.dev157.dist-info/entry_points.txt
quex_hsms-0.1.dev157.dist-info/top_level.txt
quex_hsms-0.1.dev157.dist-info/RECORD
