Metadata-Version: 2.1
Name: quex-hsms
Version: 0.1.dev157
Summary: Hardware security module simulator for chia bls12_381 signatures
Author-email: Richard Kiss <him@richardkiss.com>
License: Apache License
License-File: LICENSE
Requires-Dist: segno ==1.4.1
Requires-Dist: quex-chia-base ==0.1.3.dev17
Requires-Dist: quex-chialisp-puzzles ==0.1.3
Provides-Extra: dev
Requires-Dist: flake8 >=4.0.1 ; extra == 'dev'
Requires-Dist: black >=22.6 ; extra == 'dev'
Requires-Dist: pytest ; extra == 'dev'
